{
    "dish_name": "Соуси з солоними огірками",
    "description": "Рецепти різних соусів з солоними огірками, які підходять до риби, картоплі та бутербродів.",
    "ingredients": "[{\"name\": \"Майонез\", \"unit\": \"ст. л.\", \"amount\": \"4\"}, {\"name\": \"Огірок солоний\", \"unit\": \"шт.\", \"amount\": \"1\"}, {\"name\": \"Часник\", \"unit\": \"зубчик\", \"amount\": \"1\"}, {\"name\": \"Сіль\", \"unit\": null, \"amount\": \"за смаком\"}, {\"name\": \"Перець\", \"unit\": null, \"amount\": \"за смаком\"}, {\"name\": \"Огірки солоні\", \"unit\": \"шт.\", \"amount\": \"2\"}, {\"name\": \"Сметана\", \"unit\": \"ст. л.\", \"amount\": \"4\"}, {\"name\": \"Лимонний сік\", \"unit\": \"ч. л.\", \"amount\": \"0.5\"}, {\"name\": \"Куркума або солодка паприка\", \"unit\": \"ч. л.\", \"amount\": \"0.5\"}, {\"name\": \"Кріп\", \"unit\": \"пучка\", \"amount\": \"0.5\"}, {\"name\": \"Солоні огірочки\", \"unit\": \"шт.\", \"amount\": \"2-3\"}, {\"name\": \"Каперси\", \"unit\": \"ст. л.\", \"amount\": \"2\"}, {\"name\": \"Гірчиця будь-яка\", \"unit\": \"ч. л.\", \"amount\": \"1\"}, {\"name\": \"Варене яйце\", \"unit\": \"шт.\", \"amount\": \"1\"}, {\"name\": \"Солодка цибуля\", \"unit\": \"ст. л.\", \"amount\": \"1\"}, {\"name\": \"Кріп\", \"unit\": \"пучка\", \"amount\": \"1/3\"}, {\"name\": \"Огірки солоні\", \"unit\": \"шт.\", \"amount\": \"3\"}, {\"name\": \"Солодка цибуля\", \"unit\": \"цибулина\", \"amount\": \"1\"}, {\"name\": \"Гірчиця дижонська\", \"unit\": \"ч. л.\", \"amount\": \"1\"}, {\"name\": \"Оцет винний білий\", \"unit\": \"ч. л.\", \"amount\": \"1\"}, {\"name\": \"Олія\", \"unit\": \"ст. л.\", \"amount\": \"1\"}, {\"name\": \"Цукор\", \"unit\": \"ч. л.\", \"amount\": \"0.5\"}, {\"name\": \"Сіль\", \"unit\": null, \"amount\": \"за смаком\"}]",
    "instructions": "1. Соус з майонезу та солоних огірків та часнику: Огірок натираємо на дрібній тертці і віджимаємо сік. Часник трьом або продавлюємо через прес. Змішуємо з майонезом, солимо і перчимо за смаком.\n2. Сметанний соус із часником та солоним огірком: Огірки трьом на великій тертці, віджимаємо сік. Часник давимо через прес. Кріп дрібно шаткуємо. Змішуємо зі сметаною, солимо, перчимо, додаємо лимонний сік і куркуму або паприку.\n3. Соус для картоплі по-сільськи із солоним огірком: Огірки та цибулю нарубаємо дрібним кубиком. Каперси, кріп і яйце дрібно шаткуємо. Змішуємо зі сметаною та гірчицею, солимо за смаком.\n4. Соус салат з огірків з гірчицею скандинавський рецепт: Цибулю рубаємо дрібним кубиком, додаємо оцет. Огірки трьом на дрібній тертці, віджимаємо сік у цибулю, маринуємо 10 хвилин. Зливаємо рідину, змішуємо з огірками та іншими інгредієнтами, солимо за потребою.",
    "category": "Соус",
    "prep_time": null,
    "cook_time": null,
    "total_time": null,
    "notes": "Можна додавати зелень, робити соус гострішим, замінювати майонез домашнім. Соуси підходять до риби, картоплі, бутербродів, салатів.",
    "tags": "соус, солоні огірки, майонез, сметана, часник, кріп, гірчиця"
}