{
    "dish_name": "Ριζότο µε κυπριακές µαύρες ελιές ντοµάτες φασολάκια και λεµόνι",
    "description": "Ριζότο με κυπριακές μαύρες ελιές, ντομάτες, φασολάκια και λεμόνι.",
    "ingredients": "[{\"name\": \"ρύζι Arborio\", \"units\": \"φλ.\", \"amount\": 1}, {\"name\": \"κρεµµύδι ψιλοκοµµένο\", \"units\": \"φλ.\", \"amount\": 0.5}, {\"name\": \"λευκό κρασί\", \"units\": \"φλ.\", \"amount\": 1}, {\"name\": \"ζωµό λαχανικών\", \"units\": \"λίτρο\", \"amount\": 1}, {\"name\": \"πράσινα φασολάκια\", \"units\": \"φλ.\", \"amount\": 1}, {\"name\": \"ντοµατίνια\", \"units\": \"шт.\", \"amount\": 6}, {\"name\": \"φύλλο άνηθο\", \"units\": \"мικρό\", \"amount\": 1}, {\"name\": \"μαύρες ελιές\", \"units\": \"шт.\", \"amount\": 8}, {\"name\": \"χυµός από λεµόνι\", \"units\": \"мικρό\", \"amount\": 1}, {\"name\": \"κρέµα γάλακτος\", \"units\": \"φλ.\", \"amount\": 0.25}, {\"name\": \"παρµεζάνα τριµµένη\", \"units\": \"κουταλιές\", \"amount\": 2}, {\"name\": \"βούτυρο\", \"units\": \"κουταλιά\", \"amount\": 1}]",
    "instructions": "Σοτάρετε τα κρεµµύδια µέχρι να γίνουν διάφανα και προσθέτετε το ρύζι. Προσθέτετε το λευκό κρασί σιγά-σιγά και ανακατεύετε. Σταδιακά προσθέτετε λίγο ζωµό και ανακατεύετε. Προσθέτετε τα ντοµατίνια και ανακατεύετε. Προσθέτετε τις ελιές και τελευταία τα πράσινα φασολάκια. Στη συνέχεια, προσθέτετε το χυµό λεµονιού και το αφήνετε να εξατµιστεί. Προσθέτετε στο τέλος την κρέµα γάλακτος και την τριµµένη παρµεζάνα, ανακατεύετε ελαφρά, αλατοπιπερώνετε και σερβίρετε αµέσως.",
    "category": "Main Course",
    "prep_time": null,
    "cook_time": null,
    "total_time": null,
    "notes": null,
    "tags": "ριζότο, κυπριακή κουζίνα, φαγητό"
}