{
    "dish_name": "Gulaš",
    "description": "Recept za gulaš s detaljnim uputama kako pripremiti savršeno jelo bogatog okusa i sočnosti, koristeći kvalitetno meso i savršenu kombinaciju začina.",
    "ingredients": "[{\"name\": \"juneće meso\", \"unit\": \"kg\", \"amount\": \"1\"}, {\"name\": \"glavice luka\", \"unit\": \"veće\", \"amount\": \"2\"}, {\"name\": \"češnja češnjaka\", \"unit\": null, \"amount\": \"3\"}, {\"name\": \"mrkve\", \"unit\": null, \"amount\": \"2\"}, {\"name\": \"svježe paprike (crvena i zelena)\", \"unit\": null, \"amount\": \"2\"}, {\"name\": \"sjeckana rajčica\", \"unit\": \"g\", \"amount\": \"400\"}, {\"name\": \"crno vino\", \"unit\": \"ml\", \"amount\": \"200\"}, {\"name\": \"goveđi temeljac\", \"unit\": \"l\", \"amount\": \"1\"}, {\"name\": \"svinjska mast ili ulje\", \"unit\": \"žlice\", \"amount\": \"2\"}, {\"name\": \"slatka paprika\", \"unit\": \"žlica\", \"amount\": \"1\"}, {\"name\": \"ljuta paprika\", \"unit\": \"žličica\", \"amount\": \"1\"}, {\"name\": \"kumin\", \"unit\": \"žličica\", \"amount\": \"1\"}, {\"name\": \"lovorov list\", \"unit\": null, \"amount\": \"1\"}, {\"name\": \"mljeveni papar\", \"unit\": \"žličice\", \"amount\": \"0.5\"}, {\"name\": \"sol\", \"unit\": null, \"amount\": null}, {\"name\": \"timijan\", \"unit\": \"žličice\", \"amount\": \"0.5\"}, {\"name\": \"majoran\", \"unit\": \"žličice\", \"amount\": \"0.5\"}, {\"name\": \"srednji krumpiri\", \"unit\": null, \"amount\": \"2\"}, {\"name\": \"brašno\", \"unit\": \"žlica\", \"amount\": \"1\"}]",
    "instructions": "1. Meso narežite na kocke veličine oko 3 cm. Luk sitno nasjeckajte, češnjak zgnječite, a mrkvu i papriku narežite na tanke trakice. 2. U loncu zagrijte mast ili ulje i dodajte nasjeckani luk. Pirjajte luk 15-20 minuta na laganoj vatri dok ne postane zlatno-smeđi. 3. Dodajte meso i pojačajte vatru. Pirjajte meso dok ne dobije smeđu boju sa svih strana. Dodajte papriku u prahu, sol, papar, kumin, lovorov list i timijan, pa promiješajte. 4. Ulijte crno vino i pustite da alkohol ispari. Dodajte nasjeckanu mrkvu, papriku, češnjak i rajčicu. 5. Ulijte goveđi temeljac ili vodu, poklopite i kuhajte najmanje 2 sata uz povremeno miješanje. 6. Za gušći gulaš dodajte krumpir narezan na kockice i kuhajte još 30 minuta. Po želji umiješajte brašno s malo vode i dodajte u gulaš.",
    "category": "Main Course",
    "prep_time": null,
    "cook_time": "2 hours 30 minutes",
    "total_time": null,
    "notes": "Koristite kvalitetno meso s malo masnoće. Luk pirjajte dugo i polako za bogat okus. Vino dodaje dubinu okusa. Pustite gulaš da odstoji sat vremena prije posluživanja. Recept se može prilagoditi različitim vrstama mesa i začina.",
    "tags": "gulaš, juneće meso, goveđi gulaš, svinjski gulaš, recept, glavno jelo"
}